score.varnish-0.3.1-py3.4-nspkg.pth
score/varnish/__init__.py
score/varnish/_conf.py
score/varnish/_init.py
score/varnish/cli.py
score.varnish-0.3.1.dist-info/DESCRIPTION.rst
score.varnish-0.3.1.dist-info/METADATA
score.varnish-0.3.1.dist-info/RECORD
score.varnish-0.3.1.dist-info/WHEEL
score.varnish-0.3.1.dist-info/entry_points.txt
score.varnish-0.3.1.dist-info/metadata.json
score.varnish-0.3.1.dist-info/namespace_packages.txt
score.varnish-0.3.1.dist-info/top_level.txt
